connectorctl/__init__.py
connectorctl/cli.py
connectorctl-0.1.0.dist-info/METADATA
connectorctl-0.1.0.dist-info/WHEEL
connectorctl-0.1.0.dist-info/entry_points.txt
connectorctl-0.1.0.dist-info/licenses/LICENSE
connectorctl-0.1.0.dist-info/RECORD
