Metadata-Version: 2.3
Name: connectorctl
Version: 0.1.0
Summary: Kafka Connector Management tool
Author-email: GirishCodeAlchemy <girishcodealchemy@gmail.com>
License: MIT License
License-File: LICENSE
Classifier: Intended Audience :: Developers
Classifier: License :: OSI Approved :: MIT License
Classifier: Programming Language :: Python :: 3
Classifier: Topic :: Software Development :: Build Tools
Requires-Python: >=3.8
Requires-Dist: python-dotenv>=1.0.1
Requires-Dist: requests==2.32.3
Requires-Dist: tabulate==0.9.0
Provides-Extra: docs
